MANIFEST.in
README.md
setup.cfg
setup.py
Manteia/ActiveLearning.py
Manteia/Augmentation.py
Manteia/Classification.py
Manteia/Dataset.py
Manteia/Generation.py
Manteia/Model.py
Manteia/Preprocess.py
Manteia/Statistic.py
Manteia/Summarize.py
Manteia/Task.py
Manteia/Utils.py
Manteia/Visualisation.py
Manteia/__init__.py
Manteia.egg-info/PKG-INFO
Manteia.egg-info/SOURCES.txt
Manteia.egg-info/dependency_links.txt
Manteia.egg-info/entry_points.txt
Manteia.egg-info/requires.txt
Manteia.egg-info/top_level.txt