Metadata-Version: 2.1
Name: Manteia
Version: 0.0.35
Summary: deep learning,NLP,classification,text,bert,distilbert,albert,xlnet,roberta,gpt2,torch,pytorch,active learning,augmentation,data
Home-page: https://pypi.org/project/Manteia/
Author: Yves Mercadier
Author-email: manteia.ym001@gmail.com
License: UNKNOWN
Project-URL: Pypi, https://pypi.org/project/Manteia/
Project-URL: Documentation, https://manteia.readthedocs.io/en/latest/index.html
Project-URL: Source Code, https://github.com/ym001/Manteia
Platform: UNKNOWN
Classifier: Programming Language :: Python
Classifier: Development Status :: 1 - Planning
Classifier: License :: OSI Approved :: MIT License
Classifier: Natural Language :: English
Classifier: Operating System :: OS Independent
Classifier: Programming Language :: Python :: 3.6
Classifier: Topic :: Scientific/Engineering :: Artificial Intelligence
Classifier: Topic :: Text Processing
Classifier: Topic :: Scientific/Engineering
Classifier: Topic :: Scientific/Engineering :: Mathematics
Classifier: Topic :: Software Development
Classifier: Topic :: Software Development :: Libraries
Classifier: Topic :: Software Development :: Libraries :: Python Modules
